[
  { "name": "pork tenderloin", "intensity": 3, "cookingMethods": ["roasted", "seared", "grilled"],
    "description": "The leanest, most tender cut of the pig — quick to roast, quicker to overcook; a spice crust or glaze does it real favors." },
  { "name": "ribs", "intensity": 6, "cookingMethods": ["smoked", "braised", "grilled", "roasted", "baked"],
    "description": "Bone, fat, and connective tissue that time turns to glory — low and slow until the meat barely clings, then sauce and fire." },
  { "name": "ribeye", "intensity": 6, "cookingMethods": ["grilled", "seared", "roasted"],
    "description": "The steak-lover's steak — heavily marbled, deeply beefy, self-basting over high heat; salt, fire, and rest are the whole recipe." },
  { "name": "serrano chili", "intensity": 7, "cookingMethods": ["raw", "pickled", "roasted", "sautéed"],
    "description": "Jalapeño's sharper little sibling — clean, grassy heat a solid step hotter, the working chili of fresh Mexican salsas." },
  { "name": "gochujang", "intensity": 8, "cookingMethods": [] },
  { "name": "doenjang", "intensity": 8, "cookingMethods": [] },
  { "name": "ssamjang", "intensity": 7, "cookingMethods": [] },
  { "name": "harissa", "intensity": 8, "cookingMethods": [] },
  { "name": "sambal oelek", "intensity": 8, "cookingMethods": [] },
  { "name": "chili crisp", "intensity": 8, "cookingMethods": [] },
  { "name": "shrimp paste", "intensity": 10, "cookingMethods": ["fermented", "toasted"] },
  { "name": "yuzu kosho", "intensity": 8, "cookingMethods": [] },
  { "name": "XO sauce", "intensity": 8, "cookingMethods": [] },
  { "name": "fermented black beans", "intensity": 8, "cookingMethods": ["fermented"] },
  { "name": "gochugaru", "intensity": 6, "cookingMethods": [] },
  { "name": "aleppo pepper", "intensity": 5, "cookingMethods": [] },
  { "name": "urfa biber", "intensity": 5, "cookingMethods": [] },
  { "name": "calabrian chili", "intensity": 7, "cookingMethods": [] },
  { "name": "guajillo", "intensity": 5, "cookingMethods": ["toasted", "simmered"] },
  { "name": "za'atar", "intensity": 6, "cookingMethods": [] },
  { "name": "ras el hanout", "intensity": 7, "cookingMethods": [] },
  { "name": "berbere", "intensity": 8, "cookingMethods": [] },
  { "name": "dukkah", "intensity": 5, "cookingMethods": ["toasted"] },
  { "name": "shichimi togarashi", "intensity": 6, "cookingMethods": [] },
  { "name": "furikake", "intensity": 6, "cookingMethods": [] },
  { "name": "curry powder", "intensity": 7, "cookingMethods": [] },
  { "name": "asafoetida", "intensity": 9, "cookingMethods": ["fried"] },
  { "name": "kombu", "intensity": 5, "cookingMethods": ["simmered"] },
  { "name": "bonito flakes", "intensity": 7, "cookingMethods": ["simmered", "raw"] },
  { "name": "halloumi", "intensity": 5, "cookingMethods": ["grilled", "fried", "seared"] },
  { "name": "paneer", "intensity": 2, "cookingMethods": ["fried", "simmered", "grilled", "sautéed"] },
  { "name": "cotija", "intensity": 7, "cookingMethods": ["raw"] },
  { "name": "ricotta salata", "intensity": 5, "cookingMethods": ["raw"] },
  { "name": "labneh", "intensity": 4, "cookingMethods": ["raw"] },
  { "name": "kefir", "intensity": 4, "cookingMethods": ["raw"] },
  { "name": "skyr", "intensity": 3, "cookingMethods": ["raw"] },
  { "name": "crema", "intensity": 3, "cookingMethods": ["raw"] },
  { "name": "jackfruit", "intensity": 4, "cookingMethods": ["raw", "braised", "simmered"] },
  { "name": "dragon fruit", "intensity": 2, "cookingMethods": ["raw"] },
  { "name": "rambutan", "intensity": 4, "cookingMethods": ["raw"] }
]
